taskra/__init__.py
taskra/api/__init__.py
taskra/api/auth.py
taskra/api/client.py
taskra/api/models/__init__.py
taskra/api/models/base.py
taskra/api/models/comment.py
taskra/api/models/issue.py
taskra/api/models/project.py
taskra/api/models/user.py
taskra/api/models/worklog.py
taskra/api/services/__init__.py
taskra/api/services/base.py
taskra/api/services/comments.py
taskra/api/services/issues.py
taskra/api/services/permissions.py
taskra/api/services/projects.py
taskra/api/services/reports.py
taskra/api/services/users.py
taskra/api/services/worklogs.py
taskra/cmd/__init__.py
taskra/cmd/commands/__init__.py
taskra/cmd/commands/alias_cmds.py
taskra/cmd/commands/config.py
taskra/cmd/commands/issues.py
taskra/cmd/commands/projects.py
taskra/cmd/commands/reports.py
taskra/cmd/commands/tickets.py
taskra/cmd/commands/worklogs.py
taskra/cmd/main.py
taskra/cmd/utils/__init__.py
taskra/cmd/utils/formatting.py
taskra/config/account.py
taskra/config/config_cmd.py
taskra/config/manager.py
taskra/core/__init__.py
taskra/core/comments.py
taskra/core/issues.py
taskra/core/projects.py
taskra/core/reports.py
taskra/core/tickets.py
taskra/core/users.py
taskra/core/worklogs.py
taskra/presentation/__init__.py
taskra/presentation/base.py
taskra/presentation/errors.py
taskra/presentation/issues.py
taskra/presentation/projects.py
taskra/presentation/reports.py
taskra/presentation/worklogs.py
taskra/utils/__init__.py
taskra/utils/cache.py
taskra/utils/debug.py
taskra/utils/model_adapters.py
taskra/utils/model_cache.py
taskra/utils/optimization.py
taskra/utils/serialization.py
taskra-0.1.9.dist-info/LICENSE
taskra-0.1.9.dist-info/METADATA
taskra-0.1.9.dist-info/WHEEL
taskra-0.1.9.dist-info/entry_points.txt
taskra-0.1.9.dist-info/RECORD
