Metadata-Version: 2.1
Name: taskra
Version: 0.1.9
Summary: A command-line tool for task and project management
Author: JV
Author-email: jason.viloria@outlook.com
Requires-Python: >=3.12,<4.0
Classifier: Programming Language :: Python :: 3
Classifier: Programming Language :: Python :: 3.12
Requires-Dist: click (>=8.1.7,<9.0.0)
Requires-Dist: pydantic (>=2.6.1,<3.0.0)
Requires-Dist: requests (>=2.31.0,<3.0.0)
Requires-Dist: rich (>=13.7.0,<14.0.0)
